arthur_client/__init__.py
arthur_client/__version__.py
arthur_client/api_bindings/__init__.py
arthur_client/api_bindings/api/__init__.py
arthur_client/api_bindings/api/alert_rules_v1_api.py
arthur_client/api_bindings/api/alerts_v1_api.py
arthur_client/api_bindings/api/authorization_v1_api.py
arthur_client/api_bindings/api/connector_schemas_v1_api.py
arthur_client/api_bindings/api/connectors_v1_api.py
arthur_client/api_bindings/api/custom_aggregation_tests_v1_api.py
arthur_client/api_bindings/api/custom_aggregations_v1_api.py
arthur_client/api_bindings/api/data_plane_associations_v1_api.py
arthur_client/api_bindings/api/data_planes_v1_api.py
arthur_client/api_bindings/api/data_retrieval_v1_api.py
arthur_client/api_bindings/api/datasets_v1_api.py
arthur_client/api_bindings/api/default_api.py
arthur_client/api_bindings/api/feature_flags_v1_api.py
arthur_client/api_bindings/api/groups_v1_api.py
arthur_client/api_bindings/api/jobs_v1_api.py
arthur_client/api_bindings/api/metric_functions_v1_api.py
arthur_client/api_bindings/api/metrics_v1_api.py
arthur_client/api_bindings/api/models_v1_api.py
arthur_client/api_bindings/api/o_auth_v1_api.py
arthur_client/api_bindings/api/organizations_v1_api.py
arthur_client/api_bindings/api/projects_v1_api.py
arthur_client/api_bindings/api/registration_v1_api.py
arthur_client/api_bindings/api/roles_v1_api.py
arthur_client/api_bindings/api/tasks_v1_api.py
arthur_client/api_bindings/api/unregistered_agents_v1_api.py
arthur_client/api_bindings/api/upsolve_v1_api.py
arthur_client/api_bindings/api/users_v1_api.py
arthur_client/api_bindings/api/webhooks_v1_api.py
arthur_client/api_bindings/api/workspaces_v1_api.py
arthur_client/api_bindings/api_client.py
arthur_client/api_bindings/api_response.py
arthur_client/api_bindings/configuration.py
arthur_client/api_bindings/docs/AggregationKind.md
arthur_client/api_bindings/docs/AggregationMetricType.md
arthur_client/api_bindings/docs/AggregationSpec.md
arthur_client-1.4.1777.dist-info/METADATA
arthur_client-1.4.1777.dist-info/WHEEL
arthur_client-1.4.1777.dist-info/RECORD
